camels/__init__.py
camels/data.py
camels/flycheck___init__.py
camels/processing.py
camels/pytorch.py
camels-0.0.8.dist-info/LICENSE
camels-0.0.8.dist-info/METADATA
camels-0.0.8.dist-info/WHEEL
camels-0.0.8.dist-info/top_level.txt
camels-0.0.8.dist-info/RECORD
