Metadata-Version: 2.1
Name: camels
Version: 0.0.8
Summary: Interface to the CAMELS dataset.
Home-page: https://github.com/simonpf/camels
Author: Simon Pfreundschuh
Author-email: simon.pfreundschuh@chalmers.se
License: UNKNOWN
Project-URL: Source, https://github.com/simonpf/camels/
Platform: UNKNOWN
Requires-Python: >=3.6
Requires-Dist: appdirs
Requires-Dist: numpy
Requires-Dist: pandas
Requires-Dist: matplotlib
